tkcefview/__init__.py
tkcefview/core.py
tkcefview/__pycache__/__init__.cpython-37.pyc
tkcefview/__pycache__/core.cpython-37.pyc
tkcefview/assets/__init__.py
tkcefview/assets/tkcefview.js
tkcefview/assets/tkcefview.png
tkcefview/assets/__pycache__/__init__.cpython-37.pyc
tkcefview-2022.1.4.dist-info/LICENSE
tkcefview-2022.1.4.dist-info/METADATA
tkcefview-2022.1.4.dist-info/WHEEL
tkcefview-2022.1.4.dist-info/top_level.txt
tkcefview-2022.1.4.dist-info/RECORD
