Metadata-Version: 2.1
Name: tkcefview
Version: 2022.1.4
Summary: pywebview inspired tkinter framed cefpython3
Home-page: https://github.com/eseunghwan/tkcefview
Author: eseunghwan
Author-email: shlee0920@naver.com
License: MIT license
Keywords: webview,cef,tkinter
Platform: UNKNOWN
Classifier: License :: OSI Approved :: MIT License
Classifier: Programming Language :: Python :: 3
Requires-Python: <3.8
License-File: LICENSE
Requires-Dist: cefpython3 (==66.0)
Requires-Dist: pyobjc (==7.3) ; sys_platform == "darwin"
